s8/__init__.py
s8/serialize.py
s8/core/__init__.py
s8/core/config.py
s8/core/error_handlers.py
s8/core/error_messages.py
s8/db/__init__.py
s8/db/database.py
s8/service/__init__.py
s8/service/booking_queries.py
s8/service/dashboard_service.py
s8/service/template_service.py
s8-0.2.2.dist-info/METADATA
s8-0.2.2.dist-info/WHEEL
s8-0.2.2.dist-info/top_level.txt
s8-0.2.2.dist-info/RECORD
