Metadata-Version: 2.4
Name: s8
Version: 0.2.2
Summary: Shared code and utils for backend and worker
Author: Your Name
Author-email: you@example.com
Requires-Python: >=3.10
Requires-Dist: aiohappyeyeballs==2.6.1
Requires-Dist: aiohttp==3.12.13
Requires-Dist: aiosignal==1.3.2
Requires-Dist: aiosqlite==0.21.0
Requires-Dist: annotated-types==0.7.0
Requires-Dist: anyio==4.9.0
Requires-Dist: attrs==25.3.0
Requires-Dist: audioop-lts==0.2.1
Requires-Dist: boto3==1.39.7
Requires-Dist: botocore==1.39.7
Requires-Dist: cffi==1.17.1
Requires-Dist: click==8.2.1
Requires-Dist: colorama==0.4.6
Requires-Dist: cryptography==45.0.5
Requires-Dist: discord.py==2.5.2
Requires-Dist: distlib==0.3.9
Requires-Dist: dnspython==2.7.0
Requires-Dist: ecdsa==0.19.1
Requires-Dist: email_validator==2.2.0
Requires-Dist: fastapi==0.115.14
Requires-Dist: filelock==3.18.0
Requires-Dist: frozenlist==1.7.0
Requires-Dist: greenlet==3.2.3
Requires-Dist: h11==0.16.0
Requires-Dist: httptools==0.6.4
Requires-Dist: idna==3.10
Requires-Dist: jmespath==1.0.1
Requires-Dist: jose==1.0.0
Requires-Dist: motor==3.7.0
Requires-Dist: multidict==6.6.0
Requires-Dist: platformdirs==4.3.8
Requires-Dist: propcache==0.3.2
Requires-Dist: psutil==5.9.6
Requires-Dist: pyasn1==0.6.1
Requires-Dist: pycparser==2.22
Requires-Dist: pydantic==2.11.7
Requires-Dist: pydantic_core==2.33.2
Requires-Dist: pymongo==4.14.0
Requires-Dist: python-dateutil==2.9.0.post0
Requires-Dist: python-dotenv==1.1.1
Requires-Dist: python-jose==3.5.0
Requires-Dist: python-multipart==0.0.20
Requires-Dist: pytz==2025.2
Requires-Dist: PyYAML==6.0.2
Requires-Dist: rsa==4.9.1
Requires-Dist: s3transfer==0.13.0
Requires-Dist: setuptools==80.9.0
Requires-Dist: six==1.17.0
Requires-Dist: sniffio==1.3.1
Requires-Dist: SQLAlchemy==2.0.41
Requires-Dist: starlette==0.46.2
Requires-Dist: typing-inspection==0.4.1
Requires-Dist: typing_extensions==4.14.1
Requires-Dist: urllib3==2.5.0
Requires-Dist: uvicorn==0.35.0
Requires-Dist: virtualenv==20.31.2
Requires-Dist: watchfiles==1.1.0
Requires-Dist: websockets==15.0.1
Requires-Dist: wheel==0.45.1
Requires-Dist: yarl==1.20.1
Requires-Dist: b2sdk==1.26.0
Dynamic: author
Dynamic: author-email
Dynamic: requires-dist
Dynamic: requires-python
Dynamic: summary
